{
  "schemaVersion": 1,
  "featureId": "feat_ui-flow_eac8d03c33",
  "title": "React component share-escrow",
  "summary": "React component implemented by frontend/src/components/share-escrow.tsx.",
  "kind": "ui-flow",
  "source": "react-component",
  "confidence": "medium",
  "entrypoints": [
    {
      "path": "frontend/src/components/share-escrow.tsx",
      "symbol": "share-escrow",
      "route": null,
      "command": null
    }
  ],
  "ownedFiles": [
    {
      "path": "frontend/src/components/share-escrow.tsx",
      "reason": "component implementation"
    }
  ],
  "contextFiles": [
    {
      "path": "frontend/package.json",
      "reason": "package manifest"
    }
  ],
  "tests": [],
  "tags": [
    "react",
    "component",
    "web"
  ],
  "trustBoundaries": [
    "user-input",
    "network",
    "serialization"
  ],
  "status": "pending",
  "lock": null,
  "findingIds": [],
  "patchAttemptIds": [],
  "analysisHistory": [],
  "createdAt": "2026-05-17T17:01:54.684Z",
  "updatedAt": "2026-05-17T17:01:54.684Z"
}
